<?xml version="1.0"?>
<CaseManagementOrderStatus MerchantID="thinkgeek" Name="Case Management Order Status" Date="2019-04-29T11:07:17-05:00">                                 
  <Update MerchantReferenceNumber="2019042992abc23c46" RequestID="5565527798186993104079">                                 
    <OriginalDecision>REVIEW</OriginalDecision>                                 
    <NewDecision>ACCEPT</NewDecision>                                 
    <Reviewer>gamestop_ehernandez</Reviewer>                                 
    <ReviewerComments>Bulk import based on CyberSource Decision Manager export. Original decision made at 2019-04-29T11:07:17-05:00</ReviewerComments>                                 
    <Queue>Default - Review</Queue>                                 
    <Profile>A: High Risk Orders</Profile>                                 
  </Update>                                 
</CaseManagementOrderStatus>